LICENSE.txt
MANIFEST.in
README.rst
setup.py
src/__init__.py
src/sad.py
src/sad.egg-info/PKG-INFO
src/sad.egg-info/SOURCES.txt
src/sad.egg-info/dependency_links.txt
src/sad.egg-info/top_level.txt