Metadata-Version: 1.2
Name: sad
Version: 1.0.0rc3
Summary: Spreadsheets as data: spreadsheet handling for humans
Home-page: https://github.com/rjh-python/sad
Author: RJH
Author-email: rjh.python@gmail.com
License: UNKNOWN
Keywords: spreadsheet csv excel numbers
Platform: UNKNOWN
Classifier: Development Status :: 3 - Alpha
Classifier: Intended Audience :: Developers
Classifier: Topic :: Office/Business
Classifier: Topic :: Office/Business :: Office Suites
Classifier: Topic :: Text Processing
Classifier: License :: OSI Approved :: MIT License
Classifier: Programming Language :: Python :: 3
Classifier: Programming Language :: Python :: 3.4
Classifier: Programming Language :: Python :: 3.5
Classifier: Programming Language :: Python :: 3.6
Requires-Python: >=3
